odoo/addons/sale_payment_mode_brand/README.rst
odoo/addons/sale_payment_mode_brand/__init__.py
odoo/addons/sale_payment_mode_brand/__manifest__.py
odoo/addons/sale_payment_mode_brand/i18n/sale_payment_mode_brand.pot
odoo/addons/sale_payment_mode_brand/readme/CONTRIBUTORS.rst
odoo/addons/sale_payment_mode_brand/readme/DESCRIPTION.rst
odoo/addons/sale_payment_mode_brand/readme/USAGE.rst
odoo/addons/sale_payment_mode_brand/static/description/icon.png
odoo/addons/sale_payment_mode_brand/static/description/index.html
odoo/addons/sale_payment_mode_brand/views/sale_order.xml
odoo12_addon_sale_payment_mode_brand-12.0.1.0.1.dist-info/METADATA
odoo12_addon_sale_payment_mode_brand-12.0.1.0.1.dist-info/WHEEL
odoo12_addon_sale_payment_mode_brand-12.0.1.0.1.dist-info/top_level.txt
odoo12_addon_sale_payment_mode_brand-12.0.1.0.1.dist-info/RECORD
