Metadata-Version: 2.1
Name: odoo12-addon-sale-payment-mode-brand
Version: 12.0.1.0.1
Summary: This addon limit payment mode selection is sale order to the brand allowed payment mode.
Home-page: https://github.com/OCA/brand
Author: ACSONE SA/NV,Odoo Community Association (OCA)
Author-email: support@odoo-community.org
License: AGPL-3
Platform: UNKNOWN
Classifier: Programming Language :: Python
Classifier: Framework :: Odoo
Classifier: License :: OSI Approved :: GNU Affero General Public License v3
Requires-Python: >=3.5
Requires-Dist: odoo12-addon-account-payment-mode-brand
Requires-Dist: odoo12-addon-account-payment-sale
Requires-Dist: odoo12-addon-sale-brand
Requires-Dist: odoo (<12.1dev,>=12.0a)
